LICENSE.md
MANIFEST.in
README.md
setup.cfg
setup.py
./cpss_vimeo/__init__.py
./cpss_vimeo/admin.py
./cpss_vimeo/apps.py
./cpss_vimeo/asgi.py
./cpss_vimeo/models.py
./cpss_vimeo/settings.py
./cpss_vimeo/tests.py
./cpss_vimeo/urls.py
./cpss_vimeo/views.py
./cpss_vimeo/wsgi.py
./cpss_vimeo/migrations/0001_initial.py
./cpss_vimeo/migrations/__init__.py
django_cpss_vimeo.egg-info/PKG-INFO
django_cpss_vimeo.egg-info/SOURCES.txt
django_cpss_vimeo.egg-info/dependency_links.txt
django_cpss_vimeo.egg-info/top_level.txt
docs/.gitkeep