Metadata-Version: 2.1
Name: django-cpss-vimeo
Version: 2.1.1
Summary: This is the Django component of the PyVimeo project, it implements the needed functionality to integrate PyVimeo in a Django based project.
Home-page: https://github.com/xgdfalcon/django-cpss-vimeo/
Author: CPSS by XGDFalcon®
Author-email: xgdfalcon@gmail.com
License: Apache
Platform: UNKNOWN
Classifier: Environment :: Web Environment
Classifier: Framework :: Django
Classifier: Intended Audience :: Developers
Classifier: License :: OSI Approved :: Apache Software License
Classifier: Operating System :: OS Independent
Classifier: Programming Language :: Python
Classifier: Programming Language :: Python :: 3
Classifier: Programming Language :: Python :: 3 :: Only
Classifier: Programming Language :: Python :: 3.6
Classifier: Programming Language :: Python :: 3.7
Classifier: Programming Language :: Python :: 3.8
